powerscale_rag_connector/PowerScaleDocumentLoader.py
powerscale_rag_connector/PowerScaleHelper.py
powerscale_rag_connector/PowerScalePathLoader.py
powerscale_rag_connector/PowerScaleUnstructuredLoader.py
powerscale_rag_connector/__init__.py
powerscale_rag_connector-1.0.9.dist-info/METADATA
powerscale_rag_connector-1.0.9.dist-info/WHEEL
powerscale_rag_connector-1.0.9.dist-info/licenses/LICENSE
powerscale_rag_connector-1.0.9.dist-info/RECORD
