Metadata-Version: 2.4
Name: powerscale-rag-connector
Version: 1.0.9
Summary: An open-source python library designed to enhance RAG application performance during data ingestion by skipping files that have already been processed for Dell PowerScale storage.
Project-URL: Homepage, https://github.com/dell/powerscale-rag-connector
Project-URL: Issues, https://github.com/dell/powerscale-rag-connector/issues
Project-URL: Repository, https://github.com/dell/powerscale-rag-connector.git
Author-email: Adam Brenner <adam.brenner@dell.com>, Michael Horgan <mike.horgan1@dell.com>
License-Expression: MIT
License-File: LICENSE
Keywords: Dell,OneFS,PowerScale
Classifier: Operating System :: OS Independent
Classifier: Programming Language :: Python :: 3
Requires-Python: >=3.8
Requires-Dist: elasticsearch
Requires-Dist: langchain-community
Requires-Dist: langchain-core
